ConnectFour/.DS_Store
ConnectFour/__about__.py
ConnectFour/__init__.py
ConnectFour/__pycache__/__about__.cpython-38.pyc
ConnectFour/__pycache__/__init__.cpython-38.pyc
ConnectFour/examples/example-win.gif
ConnectFour/game/__init__.py
ConnectFour/game/_game.py
ConnectFour/game/__pycache__/__init__.cpython-38.pyc
ConnectFour/game/__pycache__/_game.cpython-38.pyc
ConnectFour/hashmap/__init__.py
ConnectFour/hashmap/maximizer_best_moves.gz
ConnectFour/hashmap/minimizer_best_moves.gz
ConnectFour/hashmap/__pycache__/__init__.cpython-38.pyc
ConnectFour-0.0.3.dist-info/LICENSE
ConnectFour-0.0.3.dist-info/METADATA
ConnectFour-0.0.3.dist-info/WHEEL
ConnectFour-0.0.3.dist-info/top_level.txt
ConnectFour-0.0.3.dist-info/RECORD
