Metadata-Version: 2.1
Name: ConnectFour
Version: 0.0.3
Summary: A Fun Experiment of ConnectFour!
Home-page: https://github.com/tank-overlord/ConnectFour
Author: Tank Overlord
Author-email: TankOverLord88@gmail.com
License: MIT
Platform: UNKNOWN
Classifier: Development Status :: 3 - Alpha
Classifier: Programming Language :: Python :: 3
Classifier: Programming Language :: Python :: 3.8
Classifier: Programming Language :: Python :: 3.9
Classifier: License :: OSI Approved :: MIT License
Classifier: Operating System :: OS Independent
Requires-Python: >=3.8
